LICENSE
MANIFEST.in
README.rst
setup.cfg
setup.py
cumberbatch/__init__.py
cumberbatch/__main__.py
cumberbatch.egg-info/PKG-INFO
cumberbatch.egg-info/SOURCES.txt
cumberbatch.egg-info/dependency_links.txt
cumberbatch.egg-info/top_level.txt
test/test_cumberbatch.py