Metadata-Version: 1.1
Name: cumberbatch
Version: 0.5
Summary: Generate names similar to Benedict Cumberbatch.
Home-page: https://github.com/brandones/cumberbatch
Author: Brandon Istenes
Author-email: brandonesbox@gmail.com
License: Apache License 2.0
Download-URL: https://github.com/brandones/cumberbatch/tarball/0.5
Keywords: names,testing,fixtures,generation,generator,benedict,cumberbatch
Platform: UNKNOWN
Classifier: Development Status :: 4 - Beta
Classifier: License :: OSI Approved :: Apache Software License
